{
  "project_info": {
    "project_number": "932752861413",
    "project_id": "mynotes-flutter-project-stso",
    "storage_bucket": "mynotes-flutter-project-stso.firebasestorage.app"
  },
  "client": [
    {
      "client_info": {
        "mobilesdk_app_id": "1:932752861413:android:1e29923fa9943fd37e0c0c",
        "android_client_info": {
          "package_name": "com.portprojone.mynotes"
        }
      },
      "oauth_client": [],
      "api_key": [
        {
          "current_key": "AIzaSyDf4G4fcThoTD8CSCazXQSY_jMDDeDppNY"
        }
      ],
      "services": {
        "appinvite_service": {
          "other_platform_oauth_client": []
        }
      }
    }
  ],
  "configuration_version": "1"
}